exploface/__init__.py
exploface/analysis.py
exploface/conversions.py
exploface/extraction.py
exploface/visualization.py
exploface-0.0.0.dev6.dist-info/LICENSE
exploface-0.0.0.dev6.dist-info/METADATA
exploface-0.0.0.dev6.dist-info/WHEEL
exploface-0.0.0.dev6.dist-info/top_level.txt
exploface-0.0.0.dev6.dist-info/zip-safe
exploface-0.0.0.dev6.dist-info/RECORD
