Metadata-Version: 2.1
Name: exploface
Version: 0.0.0.dev6
Summary: A tool to analyse and convert data coming from the face analysing software Openface (Cambridge).
Home-page: https://github.com/emrecdem/exploface
Author: B.L. de Vries
Author-email: b.devries@esciencecenter.nl
License: UNKNOWN
Keywords: analysis,conversion,facial recoqnition,action units,Openface
Platform: UNKNOWN
Classifier: Development Status :: 3 - Alpha
Classifier: Programming Language :: Python :: 3
Classifier: License :: OSI Approved :: Apache Software License
Classifier: Operating System :: OS Independent
Requires-Dist: numpy
Requires-Dist: pandas
Requires-Dist: elanwriter
